creategitignore.py
creategitignore-0.2.1.dist-info/LICENSE
creategitignore-0.2.1.dist-info/METADATA
creategitignore-0.2.1.dist-info/WHEEL
creategitignore-0.2.1.dist-info/entry_points.txt
creategitignore-0.2.1.dist-info/top_level.txt
creategitignore-0.2.1.dist-info/RECORD
