Metadata-Version: 2.1
Name: creategitignore
Version: 0.2.1
Summary: Create .gitignore files for your projects
Home-page: https://github.com/dapoadedire/gitignore-cli
Author: Dapo Adedire
Author-email: <adedireadedapo19@gmail.com>
License: UNKNOWN
Keywords: gitignore,python
Platform: UNKNOWN
Classifier: Development Status :: 1 - Planning
Classifier: Intended Audience :: Developers
Classifier: Programming Language :: Python :: 3
Classifier: Operating System :: Unix
Classifier: Operating System :: MacOS :: MacOS X
Classifier: Operating System :: Microsoft :: Windows
Classifier: License :: OSI Approved :: MIT License
